MultiLayerPerceptron_AsherGarcia/MultiLayerPerceptron.py
MultiLayerPerceptron_AsherGarcia/Perceptron.py
MultiLayerPerceptron_AsherGarcia/__init__.py
multilayerperceptron_ashergarcia-0.1.0.dist-info/METADATA
multilayerperceptron_ashergarcia-0.1.0.dist-info/WHEEL
multilayerperceptron_ashergarcia-0.1.0.dist-info/licenses/LICENSE
multilayerperceptron_ashergarcia-0.1.0.dist-info/RECORD
