Metadata-Version: 2.4
Name: MultiLayerPerceptron_AsherGarcia
Version: 0.1.0
Summary: Implementación desde cero de un Perceptrón Multicapa en Python, sin librerías externas, con backpropagation y soporte para múltiples capas.
Project-URL: Homepage, https://github.com/AsherGarciaO/MultiLayerPerceptron/
Author-email: Asher <ashergarciaortiz@gmail.com>
License-Expression: MIT
License-File: LICENSE
Requires-Python: >=3.8
